pocketsphinx/__init__.py
pocketsphinx/_pocketsphinx.cp311-win_amd64.pyd
pocketsphinx/model/CMakeLists.txt
pocketsphinx/model/en-us/cmudict-en-us.dict
pocketsphinx/model/en-us/en-us/feat.params
pocketsphinx/model/en-us/en-us/mdef
pocketsphinx/model/en-us/en-us/means
pocketsphinx/model/en-us/en-us/noisedict
pocketsphinx/model/en-us/en-us/README
pocketsphinx/model/en-us/en-us/sendump
pocketsphinx/model/en-us/en-us/transition_matrices
pocketsphinx/model/en-us/en-us/variances
pocketsphinx/model/en-us/en-us-phone.lm.bin
pocketsphinx/model/en-us/en-us.lm.bin
pocketsphinx/segmenter.py
pocketsphinx-5.0.3.dist-info/METADATA
pocketsphinx-5.0.3.dist-info/WHEEL
pocketsphinx-5.0.3.dist-info/entry_points.txt
pocketsphinx-5.0.3.dist-info/licenses/LICENSE
pocketsphinx-5.0.3.dist-info/licenses/AUTHORS
pocketsphinx-5.0.3.dist-info/RECORD
