Metadata-Version: 2.1
Name: pocketsphinx
Version: 5.0.3
Summary: Official Python bindings for PocketSphinx
Keywords: asr speech
Author-Email: David Huggins-Daines <dhdaines@gmail.com>
Classifier: Development Status :: 6 - Mature
Classifier: Programming Language :: C
Classifier: Programming Language :: Cython
Classifier: Programming Language :: Python :: 3
Classifier: Programming Language :: Python :: 3.8
Classifier: Programming Language :: Python :: 3.9
Classifier: Programming Language :: Python :: 3.10
Classifier: Programming Language :: Python :: 3.11
Classifier: Programming Language :: Python :: 3.12
Classifier: License :: OSI Approved :: BSD License
Classifier: Operating System :: OS Independent
Classifier: Topic :: Multimedia :: Sound/Audio :: Speech
Project-URL: Homepage, https://github.com/cmusphinx/pocketsphinx
Project-URL: Documentation, https://pocketsphinx.readthedocs.io/en/latest/
Project-URL: Repository, https://github.com/cmusphinx/pocketsphinx.git
Project-URL: Issues, https://github.com/cmusphinx/pocketsphinx/issues
Requires-Dist: sounddevice
